Metadata-Version: 2.1
Name: mnx-math
Version: 0.1.0
Summary: A method numerical analysis package
Home-page: https://github.com/0xCamiX/mnx
Download-URL: https://github.com/0xCamiX/mnx/archive/refs/heads/main.zip
Author: 0xCamiX
Author-email: juancamilogallego70@icloud.com
License: MIT
Keywords: numerical,analysis,math,methods
License-File: LICENSE
Requires-Dist: numpy
Requires-Dist: scipy
